market_data_source-0.3.0.dist-info/METADATA
market_data_source-0.3.0.dist-info/WHEEL
market_data_source-0.3.0.dist-info/licenses/LICENSE
market_data_source/__init__.py
market_data_source/market_data_source.cp312-win_amd64.pyd
market_data_source-0.3.0.dist-info/RECORD
